ikml_doc/__init__.py
ikml_doc/ikml.py
ikml_doc/utils.py
ikml_doc-0.21.2.dist-info/METADATA
ikml_doc-0.21.2.dist-info/WHEEL
ikml_doc-0.21.2.dist-info/licenses/LICENSE
ikml_doc-0.21.2.dist-info/RECORD
