Metadata-Version: 2.4
Name: ikml-doc
Version: 0.21.2
Summary: A parser for IKML (Indic Knowledge Markup Language) Documents
Project-URL: Homepage, https://gitlab.com/siddhantakosha/public/software/ikml-pypi
Project-URL: Issues, https://gitlab.com/siddhantakosha/public/software/ikml-pypi/-/issues
Author-email: Chaitanya Lakkundi <chaitanya.lakkundi@gmail.com>, Sai Susarla <sai.susarla@gmail.com>
License-File: LICENSE
Classifier: License :: OSI Approved :: GNU Library or Lesser General Public License (LGPL)
Classifier: Programming Language :: Python :: 3.10
Classifier: Topic :: Software Development :: Libraries :: Python Modules
Requires-Python: >=3.10
Requires-Dist: anytree
Requires-Dist: requests
